{"amli_on_2nd":[{"floor_plan_name":"Benson","property_name":"amli_on_2nd","retrieved":"2014-02-01 09:31:46 -0600","square_footage":"626","bed_bath_count":"1 Bed 1 Bath","floor":"18","unit":"1-1809","pets":"Dogs, Cats","available":"Now - Mar 2","starting_rent":"$1,894"},{"floor_plan_name":"Benson","property_name":"amli_on_2nd","retrieved":"2014-02-01 09:31:47 -0600","square_footage":"626","bed_bath_count":"1 Bed 1 Bath","floor":"5","unit":"1-509","pets":"Dogs, Cats","available":"Now - Mar 2","starting_rent":"$1,929"},{"floor_plan_name":"Benson","property_name":"amli_on_2nd","retrieved":"2014-02-01 09:31:47 -0600","square_footage":"626","bed_bath_count":"1 Bed 1 Bath","floor":"15","unit":"1-1503","pets":"Dogs, Cats","available":"Feb 8 - Mar 9","starting_rent":"$1,824"},{"floor_plan_name":"Price","property_name":"amli_on_2nd","retrieved":"2014-02-01 09:31:49 -0600","square_footage":"953","bed_bath_count":"1 Bed 1 Bath","floor":"11","unit":"1-1113","pets":"Dogs, Cats","available":"Now - Mar 2","starting_rent":"$2,315"},{"floor_plan_name":"Price","property_name":"amli_on_2nd","retrieved":"2014-02-01 09:31:49 -0600","square_footage":"953","bed_bath_count":"1 Bed 1 Bath","floor":"17","unit":"1-1713","pets":"Dogs, Cats","available":"Now - Mar 2","starting_rent":"$2,435"},{"floor_plan_name":"Price","property_name":"amli_on_2nd","retrieved":"2014-02-01 09:31:49 -0600","square_footage":"953","bed_bath_count":"1 Bed 1 Bath","floor":"17","unit":"1-1715","pets":"Dogs, Cats","available":"Now - Mar 2","starting_rent":"$2,535"},{"floor_plan_name":"Holly","property_name":"amli_on_2nd","retrieved":"2014-02-01 09:31:52 -0600","square_footage":"746","bed_bath_count":"1 Bed 1 Bath","floor":"10","unit":"1-1012","pets":"Dogs, Cats","available":"Now - Mar 2","starting_rent":"$2,150"},{"floor_plan_name":"Holly","property_name":"amli_on_2nd","retrieved":"2014-02-01 09:31:52 -0600","square_footage":"746","bed_bath_count":"1 Bed 1 Bath","floor":"19","unit":"1-1906","pets":"Dogs, Cats","available":"Now - Mar 2","starting_rent":"$2,285"},{"floor_plan_name":"Holly","property_name":"amli_on_2nd","retrieved":"2014-02-01 09:31:52 -0600","square_footage":"746","bed_bath_count":"1 Bed 1 Bath","floor":"T","unit":"1-312","pets":"Dogs, Cats","available":"Feb 15 - Mar 16","starting_rent":"$1,970"},{"floor_plan_name":"Nelson","property_name":"amli_on_2nd","retrieved":"2014-02-01 09:31:54 -0600","square_footage":"1187","bed_bath_count":"2 Bed 2 Bath","floor":"7","unit":"1-708","pets":"Dogs, Cats","available":"Now - Mar 2","starting_rent":"$2,731"},{"floor_plan_name":"Nelson","property_name":"amli_on_2nd","retrieved":"2014-02-01 09:31:55 -0600","square_footage":"1187","bed_bath_count":"2 Bed 2 Bath","floor":"8","unit":"1-808","pets":"Dogs, Cats","available":"Now - Mar 2","starting_rent":"$2,781"},{"floor_plan_name":"Nelson","property_name":"amli_on_2nd","retrieved":"2014-02-01 09:31:55 -0600","square_footage":"1187","bed_bath_count":"2 Bed 2 Bath","floor":"14","unit":"1-1410","pets":"Dogs, Cats","available":"Mar 7 - Apr 5","starting_rent":"$2,886"},{"floor_plan_name":"Vaughn","property_name":"amli_on_2nd","retrieved":"2014-02-01 09:31:57 -0600","square_footage":"1380","bed_bath_count":"2 Bed 2 Bath","floor":"5","unit":"1-500","pets":"Dogs, Cats","available":"Now - Mar 2","starting_rent":"$2,990"},{"floor_plan_name":"Vaughn","property_name":"amli_on_2nd","retrieved":"2014-02-01 09:31:57 -0600","square_footage":"1380","bed_bath_count":"2 Bed 2 Bath","floor":"2","unit":"1-200","pets":"Dogs, Cats","available":"Mar 2 - Mar 31","starting_rent":"$3,075"},{"floor_plan_name":"Vaughn","property_name":"amli_on_2nd","retrieved":"2014-02-01 09:31:57 -0600","square_footage":"1380","bed_bath_count":"2 Bed 2 Bath","floor":"19","unit":"1-1902","pets":"Dogs, Cats","available":"Mar 9 - Apr 7","starting_rent":"$3,405"}],"amli_5350":[{"floor_plan_name":"Hyde Park","property_name":"amli_5350","retrieved":"2014-02-01 09:32:04 -0600","square_footage":"835","bed_bath_count":"1 Bed 1 Bath","floor":"2","unit":"01-216","pets":"Dogs, Cats","available":"Now - Mar 2","starting_rent":"$1,433"},{"floor_plan_name":"Hyde Park","property_name":"amli_5350","retrieved":"2014-02-01 09:32:04 -0600","square_footage":"835","bed_bath_count":"1 Bed 1 Bath","floor":"1","unit":"01-130","pets":"Dogs, Cats","available":"Now - Mar 2","starting_rent":"$1,513"},{"floor_plan_name":"Hyde Park","property_name":"amli_5350","retrieved":"2014-02-01 09:32:04 -0600","square_footage":"835","bed_bath_count":"1 Bed 1 Bath","floor":"4","unit":"01-430","pets":"Dogs, Cats","available":"Now - Mar 2","starting_rent":"$1,538"},{"floor_plan_name":"Clarksville","property_name":"amli_5350","retrieved":"2014-02-01 09:32:06 -0600","square_footage":"776","bed_bath_count":"1 Bed 1 Bath","floor":"2","unit":"01-202","pets":"Dogs, Cats","available":"Mar 4 - Apr 2","starting_rent":"$1,306"},"error_in_scrape"],"amli_downtown":[{"floor_plan_name":"Brazos","property_name":"amli_downtown","retrieved":"2014-02-01 09:32:12 -0600","square_footage":"991","bed_bath_count":"1 Bed 1 Bath","floor":"3","unit":"03-0324","pets":"Dogs, Cats","available":"Mar 2 - Mar 31","starting_rent":"$2,260"},{"floor_plan_name":"Brazos","property_name":"amli_downtown","retrieved":"2014-02-01 09:32:13 -0600","square_footage":"991","bed_bath_count":"1 Bed 1 Bath","floor":"7","unit":"07-0724","pets":"Dogs, Cats","available":"Mar 16 - Apr 14","starting_rent":"$2,305"},{"floor_plan_name":"Brazos","property_name":"amli_downtown","retrieved":"2014-02-01 09:32:13 -0600","square_footage":"991","bed_bath_count":"1 Bed 1 Bath","floor":"2","unit":"02-0224","pets":"Dogs, Cats","available":"Apr 13 - May 12","starting_rent":"$2,330"},{"floor_plan_name":"San Antonio","property_name":"amli_downtown","retrieved":"2014-02-01 09:32:15 -0600","square_footage":"920","bed_bath_count":"1 Bed 1 Bath","floor":"4","unit":"04-0426","pets":"Dogs, Cats","available":"Apr 8 - May 7","starting_rent":"$2,098"},{"floor_plan_name":"White River","property_name":"amli_downtown","retrieved":"2014-02-01 09:32:17 -0600","square_footage":"918","bed_bath_count":"1 Bed 1 Bath","floor":"6","unit":"06-0640","pets":"Dogs, Cats","available":"Feb 6 - Mar 7","starting_rent":"$2,292"},{"floor_plan_name":"White River","property_name":"amli_downtown","retrieved":"2014-02-01 09:32:17 -0600","square_footage":"918","bed_bath_count":"1 Bed 1 Bath","floor":"2","unit":"02-0220","pets":"Dogs, Cats","available":"Mar 22 - Apr 20","starting_rent":"$2,137"},{"floor_plan_name":"Sabine","property_name":"amli_downtown","retrieved":"2014-02-01 09:32:19 -0600","square_footage":"691","bed_bath_count":"1 Bed 1 Bath","floor":"5","unit":"05-0522","pets":"Dogs, Cats","available":"Mar 16 - Apr 14","starting_rent":"$1,907"},{"floor_plan_name":"Pecos","property_name":"amli_downtown","retrieved":"2014-02-01 09:32:22 -0600","square_footage":"835","bed_bath_count":"1 Bed 1 Bath","floor":"3","unit":"03-0328","pets":"Dogs, Cats","available":"Mar 23 - Apr 21","starting_rent":"$2,119"},{"floor_plan_name":"Canadian","property_name":"amli_downtown","retrieved":"2014-02-01 09:32:24 -0600","square_footage":"1276","bed_bath_count":"2 Bed 2 Bath","floor":"5","unit":"05-0515","pets":"Dogs, Cats","available":"Feb 16 - Mar 17","starting_rent":"$2,755"},{"floor_plan_name":"Trinity","property_name":"amli_downtown","retrieved":"2014-02-01 09:32:26 -0600","square_footage":"1262","bed_bath_count":"2 Bed 2 Bath","floor":"7","unit":"07-0741","pets":"Dogs, Cats","available":"Now - Mar 2","starting_rent":"$2,781"}],"amli_south_shore":[{"floor_plan_name":"Zilker","property_name":"amli_south_shore","retrieved":"2014-02-01 09:32:32 -0600","square_footage":"777","bed_bath_count":"1 Bed 1 Bath","floor":"4","unit":"2-4011","pets":"Dogs, Cats","available":"Now - Mar 2","starting_rent":"$1,382"},{"floor_plan_name":"Zilker","property_name":"amli_south_shore","retrieved":"2014-02-01 09:32:32 -0600","square_footage":"777","bed_bath_count":"1 Bed 1 Bath","floor":"5","unit":"2-5011","pets":"Dogs, Cats","available":"Now - Mar 2","starting_rent":"$1,397"},{"floor_plan_name":"Zilker","property_name":"amli_south_shore","retrieved":"2014-02-01 09:32:33 -0600","square_footage":"777","bed_bath_count":"1 Bed 1 Bath","floor":"5","unit":"2-5017","pets":"Dogs, Cats","available":"Now - Mar 2","starting_rent":"$1,442"},{"floor_plan_name":"Paramount","property_name":"amli_south_shore","retrieved":"2014-02-01 09:32:34 -0600","square_footage":"922","bed_bath_count":"1 Bed 1 Bath","floor":"4","unit":"2-4020","pets":"Dogs, Cats","available":"Mar 8 - Apr 6","starting_rent":"$1,652"},{"floor_plan_name":"Paramount","property_name":"amli_south_shore","retrieved":"2014-02-01 09:32:35 -0600","square_footage":"922","bed_bath_count":"1 Bed 1 Bath","floor":"5","unit":"2-5020","pets":"Dogs, Cats","available":"Apr 22 - May 21","starting_rent":"$1,622"},"error_in_scrape"],"amli_lantana_hills":[{"floor_plan_name":"Drake","property_name":"amli_lantana_hills","retrieved":"2014-02-01 09:32:41 -0600","square_footage":"875","bed_bath_count":"1 Bed 1 Bath","floor":"3","unit":"26-2635","pets":"Dogs, Cats","available":"Now - Mar 2","starting_rent":"$1,121"},{"floor_plan_name":"Drake","property_name":"amli_lantana_hills","retrieved":"2014-02-01 09:32:41 -0600","square_footage":"875","bed_bath_count":"1 Bed 1 Bath","floor":"1","unit":"20-2016","pets":"Dogs, Cats","available":"Now - Mar 2","starting_rent":"$1,136"},{"floor_plan_name":"Drake","property_name":"amli_lantana_hills","retrieved":"2014-02-01 09:32:41 -0600","square_footage":"875","bed_bath_count":"1 Bed 1 Bath","floor":"1","unit":"24-2415","pets":"Dogs, Cats","available":"Now - Mar 2","starting_rent":"$1,221"},{"floor_plan_name":"Waldorf","property_name":"amli_lantana_hills","retrieved":"2014-02-01 09:32:43 -0600","square_footage":"754","bed_bath_count":"1 Bed 1 Bath","floor":"1","unit":"19-1916","pets":"Dogs, Cats","available":"Now - Mar 2","starting_rent":"$1,117"},{"floor_plan_name":"Waldorf","property_name":"amli_lantana_hills","retrieved":"2014-02-01 09:32:43 -0600","square_footage":"754","bed_bath_count":"1 Bed 1 Bath","floor":"3","unit":"16-1634","pets":"Dogs, Cats","available":"Mar 22 - Apr 20","starting_rent":"$1,022"},{"floor_plan_name":"Waldorf","property_name":"amli_lantana_hills","retrieved":"2014-02-01 09:32:43 -0600","square_footage":"754","bed_bath_count":"1 Bed 1 Bath","floor":"3","unit":"19-1936","pets":"Dogs, Cats","available":"Mar 23 - Apr 21","starting_rent":"$1,002"},{"floor_plan_name":"Wilmington","property_name":"amli_lantana_hills","retrieved":"2014-02-01 09:32:45 -0600","square_footage":"1144","bed_bath_count":"2 Bed 2 Bath","floor":"3","unit":"19-1938","pets":"Dogs, Cats","available":"Now - Mar 2","starting_rent":"$1,281"},{"floor_plan_name":"Wilmington","property_name":"amli_lantana_hills","retrieved":"2014-02-01 09:32:45 -0600","square_footage":"1144","bed_bath_count":"2 Bed 2 Bath","floor":"3","unit":"19-1931","pets":"Dogs, Cats","available":"Now - Mar 2","starting_rent":"$1,321"},{"floor_plan_name":"Wilmington","property_name":"amli_lantana_hills","retrieved":"2014-02-01 09:32:46 -0600","square_footage":"1144","bed_bath_count":"2 Bed 2 Bath","floor":"3","unit":"23-2337","pets":"Dogs, Cats","available":"Now - Mar 2","starting_rent":"$1,396"}],"amli_300":[{"floor_plan_name":"E100","property_name":"amli_300","retrieved":"2014-02-01 09:32:52 -0600","square_footage":"516","bed_bath_count":"Studio 1 Bath","floor":"1","unit":"01-141","pets":"Dogs, Cats","available":"Now - Mar 2","starting_rent":"$1,383"},{"floor_plan_name":"A210","property_name":"amli_300","retrieved":"2014-02-01 09:32:53 -0600","square_footage":"676","bed_bath_count":"1 Bed 1 Bath","floor":"2","unit":"01-215","pets":"Dogs, Cats","available":"Feb 11 - Mar 12","starting_rent":"$1,591"},{"floor_plan_name":"A410","property_name":"amli_300","retrieved":"2014-02-01 09:32:56 -0600","square_footage":"821","bed_bath_count":"1 Bed 1 Bath","floor":"1","unit":"01-138","pets":"Dogs, Cats","available":"Now - Mar 2","starting_rent":"$1,724"},{"floor_plan_name":"A430","property_name":"amli_300","retrieved":"2014-02-01 09:32:59 -0600","square_footage":"890","bed_bath_count":"1 Bed 1 Bath","floor":"3","unit":"01-304","pets":"Dogs, Cats","available":"Now - Mar 2","starting_rent":"$1,750"},{"floor_plan_name":"A300","property_name":"amli_300","retrieved":"2014-02-01 09:33:01 -0600","square_footage":"768","bed_bath_count":"1 Bed 1 Bath","floor":"2","unit":"01-208","pets":"Dogs, Cats","available":"Mar 4 - Apr 2","starting_rent":"$1,675"},{"floor_plan_name":"A100","property_name":"amli_300","retrieved":"2014-02-01 09:33:03 -0600","square_footage":"561","bed_bath_count":"1 Bed 1 Bath","floor":"1","unit":"01-136","pets":"Dogs, Cats","available":"Apr 8 - May 7","starting_rent":"$1,585"},{"floor_plan_name":"A100","property_name":"amli_300","retrieved":"2014-02-01 09:33:03 -0600","square_footage":"561","bed_bath_count":"1 Bed 1 Bath","floor":"3","unit":"01-328","pets":"Dogs, Cats","available":"Apr 8 - May 7","starting_rent":"$1,585"},{"floor_plan_name":"C420","property_name":"amli_300","retrieved":"2014-02-01 09:33:05 -0600","square_footage":"1079","bed_bath_count":"2 Bed 2 Bath","floor":"2","unit":"01-226","pets":"Dogs, Cats","available":"Now - Mar 2","starting_rent":"$2,361"},{"floor_plan_name":"C410","property_name":"amli_300","retrieved":"2014-02-01 09:33:08 -0600","square_footage":"1099","bed_bath_count":"2 Bed 2 Bath","floor":"1","unit":"01-004","pets":"Dogs, Cats","available":"Feb 15 - Mar 16","starting_rent":"$2,177"},{"floor_plan_name":"C730","property_name":"amli_300","retrieved":"2014-02-01 09:33:10 -0600","square_footage":"1350","bed_bath_count":"2 Bed 2 Bath","floor":"2","unit":"01-205","pets":"Dogs, Cats","available":"Apr 22 - May 21","starting_rent":"$2,314"}],"amli_eastside":[{"floor_plan_name":"A305","property_name":"amli_eastside","retrieved":"2014-02-01 09:33:16 -0600","square_footage":"762","bed_bath_count":"1 Bed 1 Bath","floor":"1","unit":"1-141","pets":"Dogs, Cats","available":"Now - Mar 2","starting_rent":"$1,448"},{"floor_plan_name":"A305","property_name":"amli_eastside","retrieved":"2014-02-01 09:33:16 -0600","square_footage":"762","bed_bath_count":"1 Bed 1 Bath","floor":"2","unit":"1-241","pets":"Dogs, Cats","available":"Now - Mar 2","starting_rent":"$1,468"},{"floor_plan_name":"A305","property_name":"amli_eastside","retrieved":"2014-02-01 09:33:16 -0600","square_footage":"762","bed_bath_count":"1 Bed 1 Bath","floor":"4","unit":"1-475","pets":"Dogs, Cats","available":"Feb 22 - Mar 23","starting_rent":"$1,528"},{"floor_plan_name":"A315","property_name":"amli_eastside","retrieved":"2014-02-01 09:33:18 -0600","square_footage":"779","bed_bath_count":"1 Bed 1 Bath","floor":"2","unit":"1-206","pets":"Dogs, Cats","available":"Now - Mar 2","starting_rent":"$1,406"},{"floor_plan_name":"A315","property_name":"amli_eastside","retrieved":"2014-02-01 09:33:18 -0600","square_footage":"779","bed_bath_count":"1 Bed 1 Bath","floor":"1","unit":"1-110","pets":"Dogs, Cats","available":"Now - Mar 2","starting_rent":"$1,496"},{"floor_plan_name":"A315","property_name":"amli_eastside","retrieved":"2014-02-01 09:33:19 -0600","square_footage":"779","bed_bath_count":"1 Bed 1 Bath","floor":"4","unit":"1-410","pets":"Dogs, Cats","available":"Mar 11 - Apr 9","starting_rent":"$1,426"},{"floor_plan_name":"A400","property_name":"amli_eastside","retrieved":"2014-02-01 09:33:21 -0600","square_footage":"811","bed_bath_count":"1 Bed 1 Bath","floor":"2","unit":"1-237","pets":"Dogs, Cats","available":"Now - Mar 2","starting_rent":"$1,521"},{"floor_plan_name":"A400","property_name":"amli_eastside","retrieved":"2014-02-01 09:33:21 -0600","square_footage":"811","bed_bath_count":"1 Bed 1 Bath","floor":"2","unit":"1-243","pets":"Dogs, Cats","available":"Feb 13 - Mar 14","starting_rent":"$1,426"},{"floor_plan_name":"A455","property_name":"amli_eastside","retrieved":"2014-02-01 09:33:24 -0600","square_footage":"896","bed_bath_count":"1 Bed 1 Bath","floor":"1","unit":"1-151","pets":"Dogs, Cats","available":"Now - Mar 2","starting_rent":"$1,570"},{"floor_plan_name":"A430","property_name":"amli_eastside","retrieved":"2014-02-01 09:33:26 -0600","square_footage":"864","bed_bath_count":"1 Bed 1 Bath","floor":"2","unit":"1-224","pets":"Dogs, Cats","available":"Now - Mar 2","starting_rent":"$1,468"},{"floor_plan_name":"A300","property_name":"amli_eastside","retrieved":"2014-02-01 09:33:28 -0600","square_footage":"740","bed_bath_count":"1 Bed 1 Bath","floor":"3","unit":"1-313","pets":"Dogs, Cats","available":"Mar 4 - Apr 2","starting_rent":"$1,358"},{"floor_plan_name":"A415","property_name":"amli_eastside","retrieved":"2014-02-01 09:33:31 -0600","square_footage":"833","bed_bath_count":"1 Bed 1 Bath","floor":"1","unit":"1-138","pets":"Dogs, Cats","available":"Feb 11 - Mar 12","starting_rent":"$1,431"},{"floor_plan_name":"B420","property_name":"amli_eastside","retrieved":"2014-02-01 09:33:33 -0600","square_footage":"985","bed_bath_count":"1 Bed 1 Bath","floor":"4","unit":"1-436","pets":"Dogs, Cats","available":"Feb 11 - Mar 12","starting_rent":"$1,628"},{"floor_plan_name":"B420","property_name":"amli_eastside","retrieved":"2014-02-01 09:33:33 -0600","square_footage":"985","bed_bath_count":"1 Bed 1 Bath","floor":"3","unit":"1-360","pets":"Dogs, Cats","available":"Mar 7 - Apr 5","starting_rent":"$1,623"},{"floor_plan_name":"B420","property_name":"amli_eastside","retrieved":"2014-02-01 09:33:33 -0600","square_footage":"985","bed_bath_count":"1 Bed 1 Bath","floor":"3","unit":"1-352","pets":"Dogs, Cats","available":"Apr 19 - May 18","starting_rent":"$1,608"},{"floor_plan_name":"A200","property_name":"amli_eastside","retrieved":"2014-02-01 09:33:35 -0600","square_footage":"670","bed_bath_count":"1 Bed 1 Bath","floor":"3","unit":"1-355","pets":"Dogs, Cats","available":"Now - Mar 2","starting_rent":"$1,366"},{"floor_plan_name":"A200","property_name":"amli_eastside","retrieved":"2014-02-01 09:33:35 -0600","square_footage":"670","bed_bath_count":"1 Bed 1 Bath","floor":"1","unit":"1-165","pets":"Dogs, Cats","available":"Now - Mar 2","starting_rent":"$1,396"},{"floor_plan_name":"A200","property_name":"amli_eastside","retrieved":"2014-02-01 09:33:36 -0600","square_footage":"670","bed_bath_count":"1 Bed 1 Bath","floor":"3","unit":"1-308","pets":"Dogs, Cats","available":"Feb 13 - Mar 14","starting_rent":"$1,316"},{"floor_plan_name":"C605","property_name":"amli_eastside","retrieved":"2014-02-01 09:33:38 -0600","square_footage":"1217","bed_bath_count":"2 Bed 2 Bath","floor":"2","unit":"1-251","pets":"Dogs, Cats","available":"Now - Mar 2","starting_rent":"$1,816"},{"floor_plan_name":"C605","property_name":"amli_eastside","retrieved":"2014-02-01 09:33:38 -0600","square_footage":"1217","bed_bath_count":"2 Bed 2 Bath","floor":"4","unit":"1-442","pets":"Dogs, Cats","available":"Now - Mar 2","starting_rent":"$1,826"},{"floor_plan_name":"C605","property_name":"amli_eastside","retrieved":"2014-02-01 09:33:38 -0600","square_footage":"1217","bed_bath_count":"2 Bed 2 Bath","floor":"2","unit":"1-242","pets":"Dogs, Cats","available":"Feb 8 - Mar 9","starting_rent":"$1,806"},{"floor_plan_name":"C610","property_name":"amli_eastside","retrieved":"2014-02-01 09:33:40 -0600","square_footage":"1272","bed_bath_count":"2 Bed 2 Bath","floor":"3","unit":"1-330","pets":"Dogs, Cats","available":"Now - Mar 2","starting_rent":"$1,823"},{"floor_plan_name":"C610","property_name":"amli_eastside","retrieved":"2014-02-01 09:33:40 -0600","square_footage":"1272","bed_bath_count":"2 Bed 2 Bath","floor":"3","unit":"1-304","pets":"Dogs, Cats","available":"Feb 8 - Mar 9","starting_rent":"$1,933"},{"floor_plan_name":"C610","property_name":"amli_eastside","retrieved":"2014-02-01 09:33:41 -0600","square_footage":"1272","bed_bath_count":"2 Bed 2 Bath","floor":"2","unit":"1-230","pets":"Dogs, Cats","available":"Mar 12 - Apr 10","starting_rent":"$1,903"},{"floor_plan_name":"C600","property_name":"amli_eastside","retrieved":"2014-02-01 09:33:43 -0600","square_footage":"1202","bed_bath_count":"2 Bed 2 Bath","floor":"1","unit":"1-103","pets":"Dogs, Cats","available":"Mar 18 - Apr 16","starting_rent":"$1,845"},{"floor_plan_name":"C720","property_name":"amli_eastside","retrieved":"2014-02-01 09:33:45 -0600","square_footage":"1373","bed_bath_count":"2 Bed 2 Bath","floor":"2","unit":"1-209","pets":"Dogs, Cats","available":"Mar 13 - Apr 11","starting_rent":"$2,181"},{"floor_plan_name":"C720","property_name":"amli_eastside","retrieved":"2014-02-01 09:33:45 -0600","square_footage":"1373","bed_bath_count":"2 Bed 2 Bath","floor":"1","unit":"1-107","pets":"Dogs, Cats","available":"Mar 15 - Apr 13","starting_rent":"$2,281"},{"floor_plan_name":"C500","property_name":"amli_eastside","retrieved":"2014-02-01 09:33:47 -0600","square_footage":"1177","bed_bath_count":"2 Bed 2 Bath","floor":"2","unit":"1-272","pets":"Dogs, Cats","available":"Apr 22 - May 21","starting_rent":"$1,778"}]}